[
  {
    "id": 1,
    "slug": "consagracao-religiosa-fffsb",
    "titulo": "Consagração Religiosa FFFSB",
    "resumo": "",
    "imagem": "articles/consagracao-religiosa-fffsb/images/IMG-20251120-WA0039.webp",
    "createdAt": "2026-01-24",
    "updatedAt": "2026-01-24",
    "contentType": "mdx"
  },
  {
    "id": 2,
    "slug": "dom-josafa-nomeia-assessor-eclesiastico-para-o-instituto-filhos-e-filhas-de-sao-bento",
    "titulo": "Dom Josafá nomeia assessor eclesiástico para o Instituto Filhos e Filhas de São Bento",
    "resumo": "",
    "imagem": "articles/dom-josafa-nomeia-assessor-eclesiastico-para-o-instituto-filhos-e-filhas-de-sao-bento/images/ASCOM-BANNER-SITE-ARQUI.webp",
    "createdAt": "2026-01-17",
    "updatedAt": "2026-01-17",
    "contentType": "mdx"
  },
  {
    "id": 3,
    "slug": "santa-missa-solene-em-honra-a-santa-escolastica",
    "titulo": "Santa Missa Solene em honra a Santa Escolástica",
    "resumo": "",
    "imagem": "articles/santa-missa-solene-em-honra-a-santa-escolastica/images/missa-fev-2024.webp",
    "createdAt": "2026-01-17",
    "updatedAt": "2026-01-17",
    "contentType": "mdx"
  },
  {
    "id": 4,
    "slug": "o-que-e-oracao",
    "titulo": "O que é Oração?",
    "resumo": "",
    "imagem": "articles/o-que-e-oracao/images/download-1-.jpeg",
    "createdAt": "2026-01-17",
    "updatedAt": "2026-01-17",
    "contentType": "mdx"
  },
  {
    "id": 5,
    "slug": "regra-de-sao-bento",
    "titulo": "Regra de São Bento",
    "resumo": "",
    "imagem": "articles/regra-de-sao-bento/images/Sao-BENTO.jpg",
    "createdAt": "2026-01-17",
    "updatedAt": "2026-01-17",
    "contentType": "mdx"
  },
  {
    "id": 6,
    "slug": "seja-voce-tambem-um-escravo-de-amor-da-santissima-virgem",
    "titulo": "Seja você também um Escravo de Amor da Santíssima Virgem!",
    "resumo": "",
    "imagem": "articles/seja-voce-tambem-um-escravo-de-amor-da-santissima-virgem/images/virgem-maria-catequistasbrasil.jpg",
    "createdAt": "2026-01-17",
    "updatedAt": "2026-01-17",
    "contentType": "mdx"
  },
  {
    "id": 7,
    "slug": "a-medalha-de-sao-bento",
    "titulo": "A medalha de São Bento",
    "resumo": "Breve resumo sobre a Medalha de São Bento",
    "imagem": "articles/a-medalha-de-sao-bento/images/MEDALHAS-preto-e-brnaco.jpg",
    "createdAt": "2026-01-17",
    "updatedAt": "2026-01-17",
    "contentType": "mdx"
  }
]
